pyoekoboxonline/__init__.py
pyoekoboxonline/client.py
pyoekoboxonline/exceptions.py
pyoekoboxonline/models.py
pyoekoboxonline/py.typed
pyoekoboxonline-0.1.0b5.dist-info/WHEEL
pyoekoboxonline-0.1.0b5.dist-info/METADATA
pyoekoboxonline-0.1.0b5.dist-info/RECORD
