Metadata-Version: 2.3
Name: pyoekoboxonline
Version: 0.1.0b5
Summary: Python client for the Ökobox Online e-commerce API - food delivery and subscription services
Keywords: api,client,delivery,ecommerce,food,oekobox,subscription
Author: Simon Domke
Author-email: Simon Domke <simon.domke@gmail.com>
Classifier: Development Status :: 4 - Beta
Classifier: Intended Audience :: Developers
Classifier: License :: OSI Approved :: MIT License
Classifier: Programming Language :: Python :: 3 :: Only
Classifier: Programming Language :: Python :: 3.11
Classifier: Programming Language :: Python :: 3.12
Classifier: Programming Language :: Python :: 3.13
Classifier: Programming Language :: Python :: 3.14
Classifier: Topic :: Office/Business :: Financial :: Point-Of-Sale
Classifier: Topic :: Software Development :: Libraries :: Python Modules
Requires-Dist: aiohttp>=3.11
Requires-Python: >=3.11
Project-URL: Bug Tracker, https://github.com/usimd/pyoekoboxonline/issues
Project-URL: Documentation, https://github.com/usimd/pyoekoboxonline#readme
Project-URL: Homepage, https://github.com/usimd/pyoekoboxonline
Project-URL: Repository, https://github.com/usimd/pyoekoboxonline
